{"cameraMode":{"drawMode":0,"name":"Shaded","section":"Shading Mode"},"sceneLighting":true,"audioPlay":false,"sceneViewState":{"m_AlwaysRefresh":false,"showFog":true,"showSkybox":true,"showFlares":true,"showImageEffects":true,"showParticleSystems":true,"showVisualEffectGraphs":true,"m_FxEnabled":true},"in2DMode":false,"pivot":{"x":-4.352234840393066,"y":4.682078838348389,"z":-5.997988700866699},"rotation":{"x":-0.1262775957584381,"y":-0.4457842707633972,"z":0.06368207186460495,"w":-0.8839133977890015},"size":0.5973706245422363,"orthographic":false}